paramnet/__init__.py
paramnet/base.py
paramnet/dict.py
paramnet/exceptions.py
paramnet/meta.py
paramnet/util.py
paramnet/view.py
paramnet/tests/__init__.py
paramnet/tests/test_paramgraph.py
paramnet/tests/test_paramnet.py
paramnet-2.3.0.dist-info/LICENSE
paramnet-2.3.0.dist-info/METADATA
paramnet-2.3.0.dist-info/WHEEL
paramnet-2.3.0.dist-info/top_level.txt
paramnet-2.3.0.dist-info/RECORD
