Metadata-Version: 2.1
Name: paramnet
Version: 2.3.0
Summary: NetworkX graphs with required node/edge parameters
Home-page: https://github.com/spcornelius/paramnet
Author: Sean P. Cornelius
Author-email: spcornelius@gmail.com
License: MIT
Platform: UNKNOWN
Classifier: Development Status :: 3 - Alpha
Classifier: Programming Language :: Python :: 3
Classifier: Programming Language :: Python :: 3.6
Classifier: Programming Language :: Python :: 3.7
Classifier: Intended Audience :: Developers
Classifier: Intended Audience :: Science/Research
Classifier: Operating System :: OS Independent
Classifier: Topic :: Software Development :: Libraries :: Python Modules
Classifier: Topic :: Scientific/Engineering :: Mathematics
Classifier: Topic :: Scientific/Engineering :: Physics
Requires-Python: >=3.6
Requires-Dist: networkx (>=2.0)
Requires-Dist: numpy
Provides-Extra: all
Requires-Dist: pytest ; extra == 'all'
Requires-Dist: pytest-pep8 ; extra == 'all'
Requires-Dist: scipy ; extra == 'all'
Provides-Extra: testing
Requires-Dist: pytest ; extra == 'testing'
Requires-Dist: pytest-pep8 ; extra == 'testing'
Requires-Dist: scipy ; extra == 'testing'
